[{
  "id": 1,
  "first_name": "Danya",
  "last_name": "Birtwistle",
  "email": "dbirtwistle0@imgur.com",
  "avatar": "https://robohash.org/perferendiseteum.jpg?size=50x50&set=set1",
  "isOwner": false
}, {
  "id": 2,
  "first_name": "Eberhard",
  "last_name": "Vicioso",
  "email": "evicioso1@buzzfeed.com",
  "avatar": "https://robohash.org/impeditsolutanon.jpg?size=50x50&set=set1",
  "isOwner": false
}, {
  "id": 3,
  "first_name": "Gaspar",
  "last_name": "Wallsworth",
  "email": "gwallsworth2@ox.ac.uk",
  "avatar": "https://robohash.org/laborumvoluptatemdolor.jpg?size=50x50&set=set1",
  "isOwner": false
}, {
  "id": 4,
  "first_name": "Tallie",
  "last_name": "Maskelyne",
  "email": "tmaskelyne3@fotki.com",
  "avatar": "https://robohash.org/laboreofficianon.jpg?size=50x50&set=set1",
  "isOwner": false
}, {
  "id": 5,
  "first_name": "Storm",
  "last_name": "Giggie",
  "email": "sgiggie4@who.int",
  "avatar": "https://robohash.org/possimusnequesed.jpg?size=50x50&set=set1",
  "isOwner": false
}, {
  "id": 6,
  "first_name": "Janina",
  "last_name": "Stockell",
  "email": "jstockell5@furl.net",
  "avatar": "https://robohash.org/eaistemodi.jpg?size=50x50&set=set1",
  "isOwner": false
}, {
  "id": 7,
  "first_name": "Linnie",
  "last_name": "Daniell",
  "email": "ldaniell6@paypal.com",
  "avatar": "https://robohash.org/maioresfugiatut.jpg?size=50x50&set=set1",
  "isOwner": false
}, {
  "id": 8,
  "first_name": "Kristofor",
  "last_name": "Hinrichs",
  "email": "khinrichs7@nymag.com",
  "avatar": "https://robohash.org/officiadoloresqui.jpg?size=50x50&set=set1",
  "isOwner": false
}, {
  "id": 9,
  "first_name": "Malynda",
  "last_name": "Kruschev",
  "email": "mkruschev8@simplemachines.org",
  "avatar": "https://robohash.org/atqueilloet.jpg?size=50x50&set=set1",
  "isOwner": false
}, {
  "id": 10,
  "first_name": "Bonnibelle",
  "last_name": "D'eath",
  "email": "bdeath9@yale.edu",
  "avatar": "https://robohash.org/animiquicumque.jpg?size=50x50&set=set1",
  "isOwner": false
}, {
  "id": 11,
  "first_name": "Pammi",
  "last_name": "Christaeas",
  "email": "pchristaeasa@netscape.com",
  "avatar": "https://robohash.org/omniscupiditateporro.jpg?size=50x50&set=set1",
  "isOwner": false
}, {
  "id": 12,
  "first_name": "Vernice",
  "last_name": "Heiss",
  "email": "vheissb@discuz.net",
  "avatar": "https://robohash.org/etdelenitiasperiores.jpg?size=50x50&set=set1",
  "isOwner": false
}, {
  "id": 13,
  "first_name": "Annabell",
  "last_name": "Gonsalo",
  "email": "agonsaloc@prlog.org",
  "avatar": "https://robohash.org/enimdictaut.jpg?size=50x50&set=set1",
  "isOwner": false
}, {
  "id": 14,
  "first_name": "Hurley",
  "last_name": "Izkovitch",
  "email": "hizkovitchd@macromedia.com",
  "avatar": "https://robohash.org/velprovidentsed.jpg?size=50x50&set=set1",
  "isOwner": false
}, {
  "id": 15,
  "first_name": "Tandy",
  "last_name": "Scotchbourouge",
  "email": "tscotchbourougee@sina.com.cn",
  "avatar": "https://robohash.org/sintcorruptirecusandae.jpg?size=50x50&set=set1",
  "isOwner": false
}, {
  "id": 16,
  "first_name": "Gavra",
  "last_name": "Mournian",
  "email": "gmournianf@hugedomains.com",
  "avatar": "https://robohash.org/adveroinventore.jpg?size=50x50&set=set1",
  "isOwner": false
}, {
  "id": 17,
  "first_name": "Tine",
  "last_name": "Wyre",
  "email": "twyreg@g.co",
  "avatar": "https://robohash.org/quamquidemaperiam.jpg?size=50x50&set=set1",
  "isOwner": false
}, {
  "id": 18,
  "first_name": "Donna",
  "last_name": "Powelee",
  "email": "dpoweleeh@house.gov",
  "avatar": "https://robohash.org/suntfugaconsequuntur.jpg?size=50x50&set=set1",
  "isOwner": false
}, {
  "id": 19,
  "first_name": "Denys",
  "last_name": "Rawstorn",
  "email": "drawstorni@cam.ac.uk",
  "avatar": "https://robohash.org/doloreinventorebeatae.jpg?size=50x50&set=set1",
  "isOwner": false
}, {
  "id": 20,
  "first_name": "Stuart",
  "last_name": "Malatalant",
  "email": "smalatalantj@imgur.com",
  "avatar": "https://robohash.org/delenitiquiratione.jpg?size=50x50&set=set1",
  "isOwner": false
}, {
  "id": 21,
  "first_name": "Herbie",
  "last_name": "Rookwell",
  "email": "hrookwellk@dmoz.org",
  "avatar": "https://robohash.org/ipsaeafugiat.jpg?size=50x50&set=set1",
  "isOwner": false
}, {
  "id": 22,
  "first_name": "Neel",
  "last_name": "Kilsby",
  "email": "nkilsbyl@bloglovin.com",
  "avatar": "https://robohash.org/ipsamnemoexplicabo.jpg?size=50x50&set=set1",
  "isOwner": false
}, {
  "id": 23,
  "first_name": "Corny",
  "last_name": "Haton",
  "email": "chatonm@chronoengine.com",
  "avatar": "https://robohash.org/saepeillumhic.jpg?size=50x50&set=set1",
  "isOwner": false
}, {
  "id": 24,
  "first_name": "Joel",
  "last_name": "Canton",
  "email": "jcantonn@usatoday.com",
  "avatar": "https://robohash.org/nisiillumatque.jpg?size=50x50&set=set1",
  "isOwner": false
}, {
  "id": 25,
  "first_name": "Meggi",
  "last_name": "Buffham",
  "email": "mbuffhamo@livejournal.com",
  "avatar": "https://robohash.org/vitaequodsimilique.jpg?size=50x50&set=set1",
  "isOwner": false
}, {
  "id": 26,
  "first_name": "Beverly",
  "last_name": "Wigfall",
  "email": "bwigfallp@zimbio.com",
  "avatar": "https://robohash.org/molestiaeidsed.jpg?size=50x50&set=set1",
  "isOwner": false
}, {
  "id": 27,
  "first_name": "Estelle",
  "last_name": "Alcoran",
  "email": "ealcoranq@walmart.com",
  "avatar": "https://robohash.org/etidut.jpg?size=50x50&set=set1",
  "isOwner": false
}, {
  "id": 28,
  "first_name": "Kenyon",
  "last_name": "Veljes",
  "email": "kveljesr@dailymotion.com",
  "avatar": "https://robohash.org/ipsumquasiaccusantium.jpg?size=50x50&set=set1",
  "isOwner": false
}, {
  "id": 29,
  "first_name": "Mareah",
  "last_name": "Mehew",
  "email": "mmehews@hexun.com",
  "avatar": "https://robohash.org/consequunturcumquequam.jpg?size=50x50&set=set1",
  "isOwner": false
}, {
  "id": 30,
  "first_name": "Adora",
  "last_name": "Chrstine",
  "email": "achrstinet@goo.gl",
  "avatar": "https://robohash.org/nullaatquos.jpg?size=50x50&set=set1",
  "isOwner": false
}, {
  "id": 31,
  "first_name": "Wayne",
  "last_name": "Pregel",
  "email": "wpregelu@yahoo.co.jp",
  "avatar": "https://robohash.org/molestiaedictaut.jpg?size=50x50&set=set1",
  "isOwner": false
}, {
  "id": 32,
  "first_name": "Sebastian",
  "last_name": "Kimmings",
  "email": "skimmingsv@nba.com",
  "avatar": "https://robohash.org/estvoluptatesest.jpg?size=50x50&set=set1",
  "isOwner": false
}, {
  "id": 33,
  "first_name": "Levin",
  "last_name": "Shier",
  "email": "lshierw@epa.gov",
  "avatar": "https://robohash.org/quietsunt.jpg?size=50x50&set=set1",
  "isOwner": false
}, {
  "id": 34,
  "first_name": "Moe",
  "last_name": "Drinkhill",
  "email": "mdrinkhillx@redcross.org",
  "avatar": "https://robohash.org/omnisetsunt.jpg?size=50x50&set=set1",
  "isOwner": false
}, {
  "id": 35,
  "first_name": "Iver",
  "last_name": "Chaudron",
  "email": "ichaudrony@godaddy.com",
  "avatar": "https://robohash.org/quodnobisodio.jpg?size=50x50&set=set1",
  "isOwner": false
}, {
  "id": 36,
  "first_name": "Saw",
  "last_name": "Bridewell",
  "email": "sbridewellz@icq.com",
  "avatar": "https://robohash.org/quasilaudantiumcorporis.jpg?size=50x50&set=set1",
  "isOwner": false
}, {
  "id": 37,
  "first_name": "Blancha",
  "last_name": "Wadhams",
  "email": "bwadhams10@bandcamp.com",
  "avatar": "https://robohash.org/eaqueetdolores.jpg?size=50x50&set=set1",
  "isOwner": false
}, {
  "id": 38,
  "first_name": "Mildred",
  "last_name": "Tavner",
  "email": "mtavner11@networkadvertising.org",
  "avatar": "https://robohash.org/sapienteautaut.jpg?size=50x50&set=set1",
  "isOwner": false
}, {
  "id": 39,
  "first_name": "Torry",
  "last_name": "Castiglio",
  "email": "tcastiglio12@patch.com",
  "avatar": "https://robohash.org/nullavelitvero.jpg?size=50x50&set=set1",
  "isOwner": false
}, {
  "id": 40,
  "first_name": "Livia",
  "last_name": "Cochrane",
  "email": "lcochrane13@prlog.org",
  "avatar": "https://robohash.org/solutatemporavoluptate.jpg?size=50x50&set=set1",
  "isOwner": false
}, {
  "id": 41,
  "first_name": "Dulcea",
  "last_name": "Spencley",
  "email": "dspencley14@yahoo.com",
  "avatar": "https://robohash.org/animiperferendisfugit.jpg?size=50x50&set=set1",
  "isOwner": false
}, {
  "id": 42,
  "first_name": "Ezra",
  "last_name": "McClean",
  "email": "emcclean15@reverbnation.com",
  "avatar": "https://robohash.org/delenitiquiipsa.jpg?size=50x50&set=set1",
  "isOwner": false
}, {
  "id": 43,
  "first_name": "Toni",
  "last_name": "Aronsohn",
  "email": "taronsohn16@mysql.com",
  "avatar": "https://robohash.org/autvoluptatemqui.jpg?size=50x50&set=set1",
  "isOwner": false
}, {
  "id": 44,
  "first_name": "Gill",
  "last_name": "Kermott",
  "email": "gkermott17@meetup.com",
  "avatar": "https://robohash.org/doloreomniseum.jpg?size=50x50&set=set1",
  "isOwner": false
}, {
  "id": 45,
  "first_name": "Ced",
  "last_name": "Ganderton",
  "email": "cganderton18@nature.com",
  "avatar": "https://robohash.org/utconsequaturest.jpg?size=50x50&set=set1",
  "isOwner": false
}, {
  "id": 46,
  "first_name": "Neely",
  "last_name": "Achromov",
  "email": "nachromov19@latimes.com",
  "avatar": "https://robohash.org/remearumut.jpg?size=50x50&set=set1",
  "isOwner": false
}, {
  "id": 47,
  "first_name": "Pancho",
  "last_name": "Tompkiss",
  "email": "ptompkiss1a@pcworld.com",
  "avatar": "https://robohash.org/voluptatibusprovidentesse.jpg?size=50x50&set=set1",
  "isOwner": false
}, {
  "id": 48,
  "first_name": "Norbie",
  "last_name": "Orvis",
  "email": "norvis1b@dailymotion.com",
  "avatar": "https://robohash.org/accusamusprovidentdoloribus.jpg?size=50x50&set=set1",
  "isOwner": false
}, {
  "id": 49,
  "first_name": "Demetrius",
  "last_name": "Eagers",
  "email": "deagers1c@yahoo.com",
  "avatar": "https://robohash.org/solutadolorsed.jpg?size=50x50&set=set1",
  "isOwner": false
}, {
  "id": 50,
  "first_name": "Bel",
  "last_name": "Palek",
  "email": "bpalek1d@sakura.ne.jp",
  "avatar": "https://robohash.org/doloremqueeteos.jpg?size=50x50&set=set1",
  "isOwner": false
}, {
  "id": 51,
  "first_name": "Murry",
  "last_name": "Patzelt",
  "email": "mpatzelt1e@sakura.ne.jp",
  "avatar": "https://robohash.org/nonquominus.jpg?size=50x50&set=set1",
  "isOwner": false
}, {
  "id": 52,
  "first_name": "Malina",
  "last_name": "Gorger",
  "email": "mgorger1f@myspace.com",
  "avatar": "https://robohash.org/inrerumea.jpg?size=50x50&set=set1",
  "isOwner": false
}, {
  "id": 53,
  "first_name": "Abe",
  "last_name": "Lilford",
  "email": "alilford1g@youku.com",
  "avatar": "https://robohash.org/doloremquoqui.jpg?size=50x50&set=set1",
  "isOwner": false
}, {
  "id": 54,
  "first_name": "Regan",
  "last_name": "Pottle",
  "email": "rpottle1h@businessweek.com",
  "avatar": "https://robohash.org/estquossunt.jpg?size=50x50&set=set1",
  "isOwner": false
}, {
  "id": 55,
  "first_name": "Douglass",
  "last_name": "Rilston",
  "email": "drilston1i@storify.com",
  "avatar": "https://robohash.org/reiciendisquiasit.jpg?size=50x50&set=set1",
  "isOwner": false
}, {
  "id": 56,
  "first_name": "Richie",
  "last_name": "de Werk",
  "email": "rdewerk1j@jimdo.com",
  "avatar": "https://robohash.org/sintnonest.jpg?size=50x50&set=set1",
  "isOwner": false
}, {
  "id": 57,
  "first_name": "Kinnie",
  "last_name": "Diggens",
  "email": "kdiggens1k@jimdo.com",
  "avatar": "https://robohash.org/sitcupiditatenihil.jpg?size=50x50&set=set1",
  "isOwner": false
}, {
  "id": 58,
  "first_name": "Kelwin",
  "last_name": "Oblein",
  "email": "koblein1l@mediafire.com",
  "avatar": "https://robohash.org/quaevoluptasdelectus.jpg?size=50x50&set=set1",
  "isOwner": false
}, {
  "id": 59,
  "first_name": "Alyssa",
  "last_name": "Spurrier",
  "email": "aspurrier1m@edublogs.org",
  "avatar": "https://robohash.org/enimsedquasi.jpg?size=50x50&set=set1",
  "isOwner": false
}, {
  "id": 60,
  "first_name": "Monroe",
  "last_name": "Kendall",
  "email": "mkendall1n@howstuffworks.com",
  "avatar": "https://robohash.org/quiautemnemo.jpg?size=50x50&set=set1",
  "isOwner": false
}, {
  "id": 61,
  "first_name": "Tedi",
  "last_name": "Blunsom",
  "email": "tblunsom1o@google.ru",
  "avatar": "https://robohash.org/nostrumanimieum.jpg?size=50x50&set=set1",
  "isOwner": false
}, {
  "id": 62,
  "first_name": "Connie",
  "last_name": "McCluskey",
  "email": "cmccluskey1p@slashdot.org",
  "avatar": "https://robohash.org/animiuttempora.jpg?size=50x50&set=set1",
  "isOwner": false
}, {
  "id": 63,
  "first_name": "Joceline",
  "last_name": "Gwyer",
  "email": "jgwyer1q@flavors.me",
  "avatar": "https://robohash.org/porrorerumasperiores.jpg?size=50x50&set=set1",
  "isOwner": false
}, {
  "id": 64,
  "first_name": "Carlene",
  "last_name": "McWhirter",
  "email": "cmcwhirter1r@ox.ac.uk",
  "avatar": "https://robohash.org/doloremqueplaceatadipisci.jpg?size=50x50&set=set1",
  "isOwner": false
}, {
  "id": 65,
  "first_name": "Jethro",
  "last_name": "Wrightem",
  "email": "jwrightem1s@yellowbook.com",
  "avatar": "https://robohash.org/doloresmagninobis.jpg?size=50x50&set=set1",
  "isOwner": false
}, {
  "id": 66,
  "first_name": "Breena",
  "last_name": "Achromov",
  "email": "bachromov1t@examiner.com",
  "avatar": "https://robohash.org/sedsitaut.jpg?size=50x50&set=set1",
  "isOwner": false
}, {
  "id": 67,
  "first_name": "Petunia",
  "last_name": "Hawkes",
  "email": "phawkes1u@blogger.com",
  "avatar": "https://robohash.org/modinisimagnam.jpg?size=50x50&set=set1",
  "isOwner": false
}, {
  "id": 68,
  "first_name": "Abbi",
  "last_name": "Scothron",
  "email": "ascothron1v@nyu.edu",
  "avatar": "https://robohash.org/utetveritatis.jpg?size=50x50&set=set1",
  "isOwner": false
}, {
  "id": 69,
  "first_name": "Lauryn",
  "last_name": "MacGaughy",
  "email": "lmacgaughy1w@liveinternet.ru",
  "avatar": "https://robohash.org/quodoloresculpa.jpg?size=50x50&set=set1",
  "isOwner": false
}, {
  "id": 70,
  "first_name": "Rianon",
  "last_name": "Woolley",
  "email": "rwoolley1x@ted.com",
  "avatar": "https://robohash.org/voluptaspariaturdolor.jpg?size=50x50&set=set1",
  "isOwner": false
}, {
  "id": 71,
  "first_name": "Filippo",
  "last_name": "Spikins",
  "email": "fspikins1y@ebay.com",
  "avatar": "https://robohash.org/ametistealias.jpg?size=50x50&set=set1",
  "isOwner": false
}, {
  "id": 72,
  "first_name": "Nowell",
  "last_name": "Leonard",
  "email": "nleonard1z@japanpost.jp",
  "avatar": "https://robohash.org/teneturdoloremeos.jpg?size=50x50&set=set1",
  "isOwner": false
}, {
  "id": 73,
  "first_name": "Hillard",
  "last_name": "Hawkyens",
  "email": "hhawkyens20@mtv.com",
  "avatar": "https://robohash.org/saepeautqui.jpg?size=50x50&set=set1",
  "isOwner": false
}, {
  "id": 74,
  "first_name": "Gilbertina",
  "last_name": "Saffin",
  "email": "gsaffin21@ed.gov",
  "avatar": "https://robohash.org/accusamusvoluptasdoloribus.jpg?size=50x50&set=set1",
  "isOwner": false
}, {
  "id": 75,
  "first_name": "Cally",
  "last_name": "Ivy",
  "email": "civy22@miitbeian.gov.cn",
  "avatar": "https://robohash.org/esseetlaudantium.jpg?size=50x50&set=set1",
  "isOwner": false
}, {
  "id": 76,
  "first_name": "Shara",
  "last_name": "Digance",
  "email": "sdigance23@odnoklassniki.ru",
  "avatar": "https://robohash.org/evenietmaximenumquam.jpg?size=50x50&set=set1",
  "isOwner": false
}, {
  "id": 77,
  "first_name": "Clemmy",
  "last_name": "Duckhouse",
  "email": "cduckhouse24@mysql.com",
  "avatar": "https://robohash.org/etetaut.jpg?size=50x50&set=set1",
  "isOwner": false
}, {
  "id": 78,
  "first_name": "Celka",
  "last_name": "Katt",
  "email": "ckatt25@discovery.com",
  "avatar": "https://robohash.org/excepturisedaspernatur.jpg?size=50x50&set=set1",
  "isOwner": false
}, {
  "id": 79,
  "first_name": "Micheal",
  "last_name": "Naseby",
  "email": "mnaseby26@usa.gov",
  "avatar": "https://robohash.org/recusandaeatmollitia.jpg?size=50x50&set=set1",
  "isOwner": false
}, {
  "id": 80,
  "first_name": "Annissa",
  "last_name": "Dawidowitz",
  "email": "adawidowitz27@dion.ne.jp",
  "avatar": "https://robohash.org/iureipsamet.jpg?size=50x50&set=set1",
  "isOwner": false
}, {
  "id": 81,
  "first_name": "Duff",
  "last_name": "Martijn",
  "email": "dmartijn28@wikia.com",
  "avatar": "https://robohash.org/velitsuntdoloremque.jpg?size=50x50&set=set1",
  "isOwner": false
}, {
  "id": 82,
  "first_name": "Sisile",
  "last_name": "Jeacock",
  "email": "sjeacock29@whitehouse.gov",
  "avatar": "https://robohash.org/eosoptioperferendis.jpg?size=50x50&set=set1",
  "isOwner": false
}, {
  "id": 83,
  "first_name": "Jock",
  "last_name": "Grogan",
  "email": "jgrogan2a@google.fr",
  "avatar": "https://robohash.org/estnihilet.jpg?size=50x50&set=set1",
  "isOwner": false
}, {
  "id": 84,
  "first_name": "Cordey",
  "last_name": "Hadwick",
  "email": "chadwick2b@zimbio.com",
  "avatar": "https://robohash.org/occaecatiquodearum.jpg?size=50x50&set=set1",
  "isOwner": false
}, {
  "id": 85,
  "first_name": "Serene",
  "last_name": "Denington",
  "email": "sdenington2c@apple.com",
  "avatar": "https://robohash.org/corruptietsapiente.jpg?size=50x50&set=set1",
  "isOwner": false
}, {
  "id": 86,
  "first_name": "Keelby",
  "last_name": "Gowanlock",
  "email": "kgowanlock2d@google.co.jp",
  "avatar": "https://robohash.org/aliquidnatusut.jpg?size=50x50&set=set1",
  "isOwner": false
}, {
  "id": 87,
  "first_name": "Kalinda",
  "last_name": "Bortolussi",
  "email": "kbortolussi2e@canalblog.com",
  "avatar": "https://robohash.org/quibusdaminmagni.jpg?size=50x50&set=set1",
  "isOwner": false
}, {
  "id": 88,
  "first_name": "Geraldine",
  "last_name": "Fairtlough",
  "email": "gfairtlough2f@163.com",
  "avatar": "https://robohash.org/exnemoimpedit.jpg?size=50x50&set=set1",
  "isOwner": false
}, {
  "id": 89,
  "first_name": "Frederick",
  "last_name": "Cornbell",
  "email": "fcornbell2g@gizmodo.com",
  "avatar": "https://robohash.org/consequaturexpeditaimpedit.jpg?size=50x50&set=set1",
  "isOwner": false
}, {
  "id": 90,
  "first_name": "Goldy",
  "last_name": "Falconer",
  "email": "gfalconer2h@constantcontact.com",
  "avatar": "https://robohash.org/eumbeataeet.jpg?size=50x50&set=set1",
  "isOwner": false
}, {
  "id": 91,
  "first_name": "Lou",
  "last_name": "Henden",
  "email": "lhenden2i@dailymail.co.uk",
  "avatar": "https://robohash.org/ipsaevenietet.jpg?size=50x50&set=set1",
  "isOwner": false
}, {
  "id": 92,
  "first_name": "Dionysus",
  "last_name": "O'Brallaghan",
  "email": "dobrallaghan2j@taobao.com",
  "avatar": "https://robohash.org/solutasintamet.jpg?size=50x50&set=set1",
  "isOwner": true
}, {
  "id": 93,
  "first_name": "Carter",
  "last_name": "Ullyatt",
  "email": "cullyatt2k@ucla.edu",
  "avatar": "https://robohash.org/autearumamet.jpg?size=50x50&set=set1",
  "isOwner": false
}, {
  "id": 94,
  "first_name": "Ches",
  "last_name": "Patkin",
  "email": "cpatkin2l@fc2.com",
  "avatar": "https://robohash.org/enimenimaliquam.jpg?size=50x50&set=set1",
  "isOwner": false
}, {
  "id": 95,
  "first_name": "Carolann",
  "last_name": "Del Dello",
  "email": "cdeldello2m@com.com",
  "avatar": "https://robohash.org/etlaudantiummolestiae.jpg?size=50x50&set=set1",
  "isOwner": false
}, {
  "id": 96,
  "first_name": "Susana",
  "last_name": "Banck",
  "email": "sbanck2n@smugmug.com",
  "avatar": "https://robohash.org/abasperioresofficiis.jpg?size=50x50&set=set1",
  "isOwner": false
}, {
  "id": 97,
  "first_name": "Kris",
  "last_name": "Clever",
  "email": "kclever2o@jalbum.net",
  "avatar": "https://robohash.org/sitculpaitaque.jpg?size=50x50&set=set1",
  "isOwner": false
}, {
  "id": 98,
  "first_name": "Shaughn",
  "last_name": "Swatheridge",
  "email": "sswatheridge2p@princeton.edu",
  "avatar": "https://robohash.org/molestiaeexcepturiomnis.jpg?size=50x50&set=set1",
  "isOwner": false
}, {
  "id": 99,
  "first_name": "Junie",
  "last_name": "Giacomini",
  "email": "jgiacomini2q@wsj.com",
  "avatar": "https://robohash.org/ducimusexpeditaplaceat.jpg?size=50x50&set=set1",
  "isOwner": false
}, {
  "id": 100,
  "first_name": "Cherilyn",
  "last_name": "Beasant",
  "email": "cbeasant2r@wikimedia.org",
  "avatar": "https://robohash.org/temporedoloresex.jpg?size=50x50&set=set1",
  "isOwner": false
}]